cyvidia_ai_utils/__init__.py
cyvidia_ai_utils/src/cross_validation/cross_validation.py
cyvidia_ai_utils/src/cross_validation/cross_validation_model/cross_validation_model.py
cyvidia_ai_utils/src/cross_validation/cross_validation_model/transformer_cross_validation_model.py
cyvidia_ai_utils/src/cross_validation/evaluation_result.py
cyvidia_ai_utils-1.0.4.dist-info/METADATA
cyvidia_ai_utils-1.0.4.dist-info/WHEEL
cyvidia_ai_utils-1.0.4.dist-info/RECORD
