Metadata-Version: 2.1
Name: cyvidia-ai-utils
Version: 1.0.4
Summary: 
Author: nvjoshi2
Author-email: nvj1300@gmail.com
Requires-Python: >=3.9,<4.0
Classifier: Programming Language :: Python :: 3
Classifier: Programming Language :: Python :: 3.9
Classifier: Programming Language :: Python :: 3.10
Classifier: Programming Language :: Python :: 3.11
Classifier: Programming Language :: Python :: 3.12
Requires-Dist: datasets (>=2.17.0,<3.0.0)
Requires-Dist: scikit-learn (>=1.4.0,<2.0.0)
Requires-Dist: transformers[torch] (>=4.37.2,<5.0.0)
